AUTHORS
CHANGELOG
LICENSE
MANIFEST.in
README
README.rst
RELEASE
ROADMAP
setup.cfg
setup.py
couchpy/__init__.py
couchpy/client.py
couchpy/couchcmd.py
couchpy/database.py
couchpy/doc.py
couchpy/httpc.py
couchpy/httperror.py
couchpy/mixins.py
couchpy/page.py
couchpy/rest.py
couchpy/utils.py
couchpy.egg-info/PKG-INFO
couchpy.egg-info/SOURCES.txt
couchpy.egg-info/dependency_links.txt
couchpy.egg-info/namespace_packages.txt
couchpy.egg-info/requires.txt
couchpy.egg-info/top_level.txt
couchpy.egg-info/zip-safe
couchpy/db/__init__.py
docs/CHANGELOG
docs/LICENSE
docs/README
docs/ROADMAP
docs/__init__.py
docs/casestudy.etx
docs/conf.py
docs/devnotes.etx
docs/guide.etx
docs/primer.etx
docs/statemachine.txt